[
  {
    "guid": "sut_vin_ele",
    "title": "з Сутиски в Вінницю (Електромережа)",
    "nav_title": "Сутиски - Вінниця (Ел. м.)",
    "table": [
      {
        "time": "6:30"
      },
      {
        "time": "6:45"
      },
      {
        "time": "7:30",
        "text": "(Окрім неділі)"
      },
      {
        "time": "7:30"
      },
      {
        "time": "8:05"
      },
      {
        "time": "8:28"
      },
      {
        "time": "9:50"
      },
      {
        "time": "10:40"
      },
      {
        "time": "11:10"
      },
      {
        "time": "12:00"
      },
      {
        "time": "13:10"
      },
      {
        "time": "13:55"
      },
      {
        "time": "14:55"
      },
      {
        "time": "15:30"
      },
      {
        "time": "16:15"
      },
      {
        "time": "17:20"
      },
      {
        "time": "18:00"
      },
      {
        "time": "18:35"
      },
      {
        "time": "19:00"
      }
    ]
  },
  {
    "guid": "vin_sut_ele",
    "title": "з Вінниці в Сутиски (Електромережа)",
    "nav_title": "Вінниця - Сутиски (Ел. м.)",
    "table": [
      {
        "time": "6:50",
        "text": "(Окрім неділі)"
      },
      {
        "time": "7:20"
      },
      {
        "time": "7:38"
      },
      {
        "time": "9:02"
      },
      {
        "time": "9:38"
      },
      {
        "time": "10:10"
      },
      {
        "time": "11:10"
      },
      {
        "time": "12:30"
      },
      {
        "time": "13:10"
      },
      {
        "time": "14:00"
      },
      {
        "time": "14:25"
      },
      {
        "time": "15:30"
      },
      {
        "time": "16:20"
      },
      {
        "time": "17:10"
      },
      {
        "time": "17:40"
      },
      {
        "time": "18:15"
      },
      {
        "time": "19:00"
      }
    ]
  },

  {
    "guid": "sut_vin_luka",
    "title": "з Сутиски в Вінницю (Лука-Мелешківська)",
    "nav_title": "Сутиски - Вінниця (Лука М.) ",
    "table": [
      {
        "time": "6:30"
      },
      {
        "time": "7:30"
      },
      {
        "time": "8:30"
      },
      {
        "time": "9:30"
      },
      {
        "time": "10:30"
      },
      {
        "time": "11:30"
      },
      {
        "time": "12:30"
      },
      {
        "time": "13:30"
      },
      {
        "time": "14:30"
      },
      {
        "time": "15:30"
      },
      {
        "time": "16:30"
      },
      {
        "time": "17:30"
      },
      {
        "time": "18:30"
      }
    ]
  },
  {
    "guid": "vin_sut_luka",
    "title": "з Вінниці в Сутиски (Лука-Мелешківська)",
    "nav_title": "Вінниця - Сутиски (Лука М.) ",
    "table": [
      {
        "time": "7:30"
      },
      {
        "time": "8:30"
      },
      {
        "time": "9:30"
      },
      {
        "time": "10:30"
      },
      {
        "time": "11:30"
      },
      {
        "time": "12:30"
      },
      {
        "time": "13:30"
      },
      {
        "time": "14:30"
      },
      {
        "time": "15:30"
      },
      {
        "time": "16:30"
      },
      {
        "time": "17:30"
      },
      {
        "time": "18:30"
      },
      {
        "time": "20:00"
      }
    ]
  },

  {
    "guid": "sut_vin_luka_h",
    "title": "з Сутиски в Вінницю (Лука-Мелешківська) вихідні",
    "nav_title": "Сутиски - Вінниця (Лука М.) вихідні",
    "table": [
      {
        "time": "6:30"
      },
      {
        "time": "7:30"
      },
      {
        "time": "8:30"
      },
      {
        "time": "9:30"
      },
      {
        "time": "10:30"
      },
      {
        "time": "11:30"
      },
      {
        "time": "12:30"
      },
      {
        "time": "13:30"
      },
      {
        "time": "14:30"
      },
      {
        "time": "15:30"
      },
      {
        "time": "16:30"
      },
      {
        "time": "17:30"
      },
      {
        "time": "18:30"
      }
    ]
  },
  {
    "guid": "vin_sut_luka_h",
    "title": "з Вінницю в Сутиски (Лука-Мелешківська) вихідні",
    "nav_title": "Вінниця - Сутиски (Лука М.) вихідні",
    "table": [
      {
        "time": "6:30"
      },
      {
        "time": "7:30"
      },
      {
        "time": "8:30"
      },
      {
        "time": "9:30"
      },
      {
        "time": "10:30"
      },
      {
        "time": "11:30"
      },
      {
        "time": "12:30"
      },
      {
        "time": "13:30"
      },
      {
        "time": "14:30"
      },
      {
        "time": "15:30"
      },
      {
        "time": "16:30"
      },
      {
        "time": "17:30"
      },
      {
        "time": "18:30"
      },
      {
        "time": "20:00"
      }
    ]
  },

  {
    "guid": "tiv_gni",
    "title": "з Тиврова в Гнівань (через Сутиски)",
    "nav_title": "Тиврів - Гнівань",
    "table": [
      {
        "time": "7:15"
      },
      {
        "time": "8:15"
      },
      {
        "time": "10:25"
      },
      {
        "time": "11:55"
      },
      {
        "time": "14:25"
      },
      {
        "time": "15:50"
      },
      {
        "time": "16:30"
      },
      {
        "time": "18:10"
      }
    ]
  },
  {
    "guid": "gni_tiv",
    "title": "з Гніваня в Тиврів (через Сутиски)",
    "nav_title": "Гнівань - Тиврів",
    "table": [
      {
        "time": "6:45"
      },
      {
        "time": "7:15"
      },
      {
        "time": "7:55"
      },
      {
        "time": "9:57"
      },
      {
        "time": "12:20"
      },
      {
        "time": "14:55"
      },
      {
        "time": "15:45"
      },
      {
        "time": "17:20"
      }
    ]
  },

  {
    "guid": "tiv_gni_h_s",
    "title": "з Тиврова в Гнівань (Субота)",
    "nav_title": "Тиврів - Гнівань (Субота)",
    "table": [
      {
        "time": "8:15"
      },
      {
        "time": "10:45"
      },
      {
        "time": "12:55"
      },
      {
        "time": "16:30"
      },
      {
        "time": "18:10"
      }
    ]
  },
  {
    "guid": "gni_tiv_h_s",
    "title": "з Гніваня в Тиврів (Субота)",
    "nav_title": "Гнівань - Тиврів (Субота)",
    "table": [
      {
        "time": "7:20"
      },
      {
        "time": "10:00"
      },
      {
        "time": "11:20"
      },
      {
        "time": "15:45"
      },
      {
        "time": "17:20"
      }
    ]
  },

  {
    "guid": "tiv_gni_h_n",
    "title": "з Тиврова в Гнівань (Неділя)",
    "nav_title": "Тиврів - Гнівань (Неділя)",
    "table": [
      {
        "time": "8:15"
      },
      {
        "time": "11:20"
      },
      {
        "time": "13:30"
      },
      {
        "time": "16:30"
      },
      {
        "time": "18:10"
      }
    ]
  },
  {
    "guid": "gni_tiv_h_n",
    "title": "з Гніваня в Тиврів (Неділя)",
    "nav_title": "Гнівань - Тиврів (Неділя)",
    "table": [
      {
        "time": "7:20"
      },
      {
        "time": "10:00"
      },
      {
        "time": "12:20"
      },
      {
        "time": "15:45"
      },
      {
        "time": "17:20"
      }
    ]
  }
]